{
  "$schema": "https://raw.githubusercontent.com/microsoft/vcpkg-tool/main/docs/vcpkg.schema.json",
  "name": "science-scipp",
  "version": "0.1.0",
  "builtin-baseline": "41c447cc210dc39aa85d4a5f58b4a1b9e573b3dc",
  "dependencies": [
    {
      "name": "quill",
      "version>=": "3.8.0"
    },
    "stduuid"
  ],
  "features": {
    "tests": {
      "description": "science scipp test suite",
      "dependencies": ["gtest"]
    }
  },
  "overrides": [
    {
      "name": "quill",
      "version": "3.8.0"
    }
  ]
}
